ljpeg/__init__.py
ljpeg/ljpeg.py
ljpeg/utils.py
ljpeg/jpegdir/CHANGES
ljpeg/jpegdir/PORTABILITY
ljpeg/jpegdir/README
ljpeg/jpegdir/SETUP
ljpeg/jpegdir/blkint.jpg
ljpeg/jpegdir/blkint.jpg.1
ljpeg/jpegdir/blkint.jpg.2
ljpeg/jpegdir/blkint.jpg.3
ljpeg/jpegdir/chendct.c
ljpeg/jpegdir/codec.c
ljpeg/jpegdir/csize.h
ljpeg/jpegdir/dct.h
ljpeg/jpegdir/doc.ps
ljpeg/jpegdir/globals.h
ljpeg/jpegdir/huffman.c
ljpeg/jpegdir/io.c
ljpeg/jpegdir/jpeg.1
ljpeg/jpegdir/jpeg.c
ljpeg/jpegdir/jpeg_static
ljpeg/jpegdir/leedct.c
ljpeg/jpegdir/lexer.l
ljpeg/jpegdir/makefile
ljpeg/jpegdir/marker.c
ljpeg/jpegdir/marker.h
ljpeg/jpegdir/nonint.jpg
ljpeg/jpegdir/param.h
ljpeg/jpegdir/prototypes.h
ljpeg/jpegdir/stream.c
ljpeg/jpegdir/stream.h
ljpeg/jpegdir/system.h
ljpeg/jpegdir/tables.h
ljpeg/jpegdir/test.3stream
ljpeg/jpegdir/test.huff
ljpeg/jpegdir/test.q
ljpeg/jpegdir/transform.c
ljpeg-3.7.1.dist-info/LICENSE.txt
ljpeg-3.7.1.dist-info/METADATA
ljpeg-3.7.1.dist-info/WHEEL
ljpeg-3.7.1.dist-info/entry_points.txt
ljpeg-3.7.1.dist-info/top_level.txt
ljpeg-3.7.1.dist-info/RECORD
