Metadata-Version: 2.1
Name: ljpeg
Version: 3.7.1
Summary: Read and transform LJPEG images
Home-page: https://github.com/sanchezcarlosjr/ljpeg
Author: sanchezcarlosjr
Author-email: 24639141+sanchezcarlosjr@users.noreply.github.com
License: MIT
Project-URL: Documentation, https://github.com/sanchezcarlosjr/ljpeg
Platform: Mac
Platform: Linux
Classifier: Development Status :: 5 - Production/Stable
Classifier: Topic :: Utilities
Classifier: Programming Language :: Python
Classifier: Programming Language :: Python :: 3
Classifier: Environment :: Console
Classifier: Intended Audience :: Developers
Classifier: License :: OSI Approved :: MIT License
Classifier: Operating System :: POSIX :: Linux
Classifier: Operating System :: Unix
Classifier: Operating System :: MacOS
License-File: LICENSE.txt
Requires-Dist: numpy (<1.25,>=1.24)
Requires-Dist: opencv-python (<4.8,>=4.7)
Requires-Dist: importlib-metadata ; python_version < "3.8"
Provides-Extra: testing
Requires-Dist: setuptools ; extra == 'testing'
Requires-Dist: pytest ; extra == 'testing'
Requires-Dist: pytest-cov ; extra == 'testing'
